tests/onepay/__init__.py
tests/onepay/test_cart.py
tests/onepay/test_error.py
tests/onepay/test_onepay.py
tests/onepay/test_refund.py
tests/onepay/test_transaction.py
tests/webpay/__init__.py
tests/webpay/plus/__init__.py
tests/webpay/plus/test_deferred_transaction.py
tests/webpay/plus/test_mall_transaction.py
tests/webpay/plus/test_transaction.py
transbank/__init__.py
transbank/__version__.py
transbank/common/__init__.py
transbank/common/headers_builder.py
transbank/common/integration_type.py
transbank/common/options.py
transbank/common/schema.py
transbank/common/model/__init__.py
transbank/error/__init__.py
transbank/error/inscription_delete_error.py
transbank/error/inscription_finish_error.py
transbank/error/inscription_start_error.py
transbank/error/inscription_status_error.py
transbank/error/invalid_amount_error.py
transbank/error/transaction_authorize_error.py
transbank/error/transaction_capture_error.py
transbank/error/transaction_commit_error.py
transbank/error/transaction_create_error.py
transbank/error/transaction_installments_error.py
transbank/error/transaction_refund_error.py
transbank/error/transaction_status_error.py
transbank/error/transbank_error.py
transbank/oneclick/__init__.py
transbank/oneclick/mall_inscription.py
transbank/oneclick/mall_transaction.py
transbank/oneclick/schema.py
transbank/oneclick/request/__init__.py
transbank/oneclick/response/__init__.py
transbank/onepay/__init__.py
transbank/onepay/cart.py
transbank/onepay/error.py
transbank/onepay/refund.py
transbank/onepay/schema.py
transbank/onepay/sign.py
transbank/onepay/transaction.py
transbank/patpass_by_webpay/__init__.py
transbank/patpass_by_webpay/schema.py
transbank/patpass_by_webpay/transaction.py
transbank/patpass_by_webpay/request/__init__.py
transbank/patpass_by_webpay/response/__init__.py
transbank/patpass_comercio/__init__.py
transbank/patpass_comercio/inscription.py
transbank/patpass_comercio/schema.py
transbank/patpass_comercio/request/__init__.py
transbank_sdk-2.0.1.dist-info/LICENSE
transbank_sdk-2.0.1.dist-info/METADATA
transbank_sdk-2.0.1.dist-info/WHEEL
transbank_sdk-2.0.1.dist-info/top_level.txt
transbank_sdk-2.0.1.dist-info/RECORD
