Metadata-Version: 2.1
Name: transbank-sdk
Version: 2.0.1
Summary: Transbank Python SDK
Home-page: https://github.com/TransbankDevelopers/transbank-sdk-python
Author: Transbank
Author-email: transbankdevelopers@continuum.cl
License: BSD 3-clause "New" or "Revised License"
Platform: UNKNOWN
Classifier: License :: OSI Approved :: BSD License
Classifier: Programming Language :: Python
Classifier: Programming Language :: Python :: 3
Classifier: Programming Language :: Python :: 3.4
Classifier: Programming Language :: Python :: 3.5
Classifier: Programming Language :: Python :: 3.6
Classifier: Programming Language :: Python :: 3.7
Classifier: Programming Language :: Python :: Implementation :: CPython
